LICENSE
MANIFEST.in
README.md
setup.py
django_media.egg-info/PKG-INFO
django_media.egg-info/SOURCES.txt
django_media.egg-info/dependency_links.txt
django_media.egg-info/not-zip-safe
django_media.egg-info/requires.txt
django_media.egg-info/top_level.txt
media/__init__.py
media/admin.py
media/exif.py
media/models.py
media/templates/base.html
media/templates/inlines/media_photo.html
media/templates/media/base_audio.html
media/templates/media/base_photos.html
media/templates/media/base_videos.html
media/templates/media/photo_detail.html
media/templates/media/photo_list.html
media/templates/media/photoset_detail.html
media/templates/media/photoset_list.html
media/templates/media/video_detail.html
media/templates/media/video_list.html
media/templates/media/videoset_detail.html
media/templates/media/videoset_list.html
media/urls/__init__.py
media/urls/photos.py
media/urls/videos.py