Metadata-Version: 1.1
Name: django-media
Version: 1.0.1
Summary: A basic Django application to store and manage media.
Home-page: https://github.com/pigmonkey/django-media
Author: Peter Hogg
Author-email: peter@havenaut.net
License: UNKNOWN
Platform: UNKNOWN
Classifier: Programming Language :: Python
Classifier: License :: OSI Approved :: BSD License
Classifier: Operating System :: OS Independent
Classifier: Development Status :: 5 - Production/Stable
Classifier: Framework :: Django
